setup.py
mess_server_app.egg-info/PKG-INFO
mess_server_app.egg-info/SOURCES.txt
mess_server_app.egg-info/dependency_links.txt
mess_server_app.egg-info/requires.txt
mess_server_app.egg-info/top_level.txt
server/__init__.py
server/server.py
server/common/__init__.py
server/common/decos.py
server/common/descryptors.py
server/common/errors.py
server/common/metaclasses.py
server/common/utils.py
server/common/variables.py
server/doc/__init__.py
server/doc/source/__init__.py
server/doc/source/conf.py
server/logs/__init__.py
server/logs/configs/__init__.py
server/logs/configs/client_log_config.py
server/logs/configs/server_log_config.py
server/server/__init__.py
server/server/add_user.py
server/server/config_window.py
server/server/core.py
server/server/database.py
server/server/main_window.py
server/server/remove_user.py
server/server/stat_window.py
server/unit_tests/__init__.py
server/unit_tests/test_client.py
server/unit_tests/test_server.py