Metadata-Version: 1.0
Name: mess-server-app
Version: 0.0.1
Summary: mess_server_app
Home-page: UNKNOWN
Author: KosarevDV
Author-email: dlinnii21@gmail.com
License: UNKNOWN
Platform: UNKNOWN
